setup.cfg
setup.py
oo_trees/__init__.py
oo_trees/attribute.py
oo_trees/classifier.py
oo_trees/confusion_matrix.py
oo_trees/dataset.py
oo_trees/decision_tree.py
oo_trees/outcome_counter.py
oo_trees/random_forest.py
oo_trees/single_attribute_splitter_finder.py
oo_trees/splitter.py
oo_trees.egg-info/PKG-INFO
oo_trees.egg-info/SOURCES.txt
oo_trees.egg-info/dependency_links.txt
oo_trees.egg-info/requires.txt
oo_trees.egg-info/top_level.txt