Metadata-Version: 1.1
Name: oo-trees
Version: 0.0.1
Summary: Object-oriented implementations of decision tree variants
Home-page: http://github.com/asross/oo_trees
Author: Andrew Ross
Author-email: andrewslavinross@gmail.com
License: Apache Software License
Platform: any
Classifier: Programming Language :: Python
Classifier: Development Status :: 3 - Alpha
Classifier: Natural Language :: English
Classifier: License :: OSI Approved :: Apache Software License
Classifier: Operating System :: OS Independent
Classifier: Intended Audience :: Developers
Classifier: Intended Audience :: Science/Research
